pylabrobot/__init__.py
pylabrobot/__version__.py
pylabrobot/machine.py
pylabrobot/serializer.py
pylabrobot/heating_shaking/__init__.py
pylabrobot/heating_shaking/backend.py
pylabrobot/heating_shaking/heater_shaker.py
pylabrobot/heating_shaking/heater_shaker_tests.py
pylabrobot/heating_shaking/inheco.py
pylabrobot/liquid_handling/__init__.py
pylabrobot/liquid_handling/errors.py
pylabrobot/liquid_handling/liquid_handler.py
pylabrobot/liquid_handling/liquid_handler_tests.py
pylabrobot/liquid_handling/standard.py
pylabrobot/liquid_handling/strictness.py
pylabrobot/liquid_handling/backends/USBBackend.py
pylabrobot/liquid_handling/backends/__init__.py
pylabrobot/liquid_handling/backends/backend.py
pylabrobot/liquid_handling/backends/chatterbox_backend.py
pylabrobot/liquid_handling/backends/chatterbox_backend_tests.py
pylabrobot/liquid_handling/backends/http.py
pylabrobot/liquid_handling/backends/http_tests.py
pylabrobot/liquid_handling/backends/opentrons_backend.py
pylabrobot/liquid_handling/backends/opentrons_backend_tests.py
pylabrobot/liquid_handling/backends/saver_backend.py
pylabrobot/liquid_handling/backends/serializing_backend.py
pylabrobot/liquid_handling/backends/serializing_backend_tests.py
pylabrobot/liquid_handling/backends/websocket.py
pylabrobot/liquid_handling/backends/websocket_tests.py
pylabrobot/liquid_handling/backends/hamilton/STAR.py
pylabrobot/liquid_handling/backends/hamilton/STAR_tests.py
pylabrobot/liquid_handling/backends/hamilton/VENUS.py
pylabrobot/liquid_handling/backends/hamilton/__init__.py
pylabrobot/liquid_handling/backends/hamilton/base.py
pylabrobot/liquid_handling/backends/hamilton/pump.py
pylabrobot/liquid_handling/backends/hamilton/tilt_module.py
pylabrobot/liquid_handling/backends/hamilton/vantage.py
pylabrobot/liquid_handling/backends/hamilton/vantage_tests.py
pylabrobot/liquid_handling/backends/tecan/EVO.py
pylabrobot/liquid_handling/backends/tecan/__init__.py
pylabrobot/liquid_handling/backends/tecan/errors.py
PyLabRobot-0.1.6.dist-info/LICENSE
PyLabRobot-0.1.6.dist-info/METADATA
PyLabRobot-0.1.6.dist-info/WHEEL
PyLabRobot-0.1.6.dist-info/entry_points.txt
PyLabRobot-0.1.6.dist-info/top_level.txt
PyLabRobot-0.1.6.dist-info/RECORD
