Metadata-Version: 2.1
Name: PyLabRobot
Version: 0.1.6
Summary: A hardware agnostic platform for lab automation
Home-page: https://github.com/pylabrobot/pylabrobot.git
License-File: LICENSE
Requires-Dist: typing_extensions
Provides-Extra: fw
Requires-Dist: pyusb; extra == "fw"
Provides-Extra: http
Requires-Dist: requests; extra == "http"
Requires-Dist: types-requests; extra == "http"
Provides-Extra: plate-reading
Requires-Dist: pylibftdi; extra == "plate-reading"
Provides-Extra: websockets
Requires-Dist: websockets; extra == "websockets"
Provides-Extra: visualizer
Requires-Dist: websockets; extra == "visualizer"
Provides-Extra: inheco
Requires-Dist: hid; extra == "inheco"
Provides-Extra: opentrons
Requires-Dist: opentrons-http-api-client; extra == "opentrons"
Requires-Dist: opentrons-shared-data; extra == "opentrons"
Provides-Extra: server
Requires-Dist: flask[async]; extra == "server"
Provides-Extra: dev
Requires-Dist: pyusb; extra == "dev"
Requires-Dist: requests; extra == "dev"
Requires-Dist: types-requests; extra == "dev"
Requires-Dist: pylibftdi; extra == "dev"
Requires-Dist: websockets; extra == "dev"
Requires-Dist: websockets; extra == "dev"
Requires-Dist: opentrons-http-api-client; extra == "dev"
Requires-Dist: opentrons-shared-data; extra == "dev"
Requires-Dist: flask[async]; extra == "dev"
Requires-Dist: hid; extra == "dev"
Requires-Dist: sphinx_book_theme; extra == "dev"
Requires-Dist: myst_nb; extra == "dev"
Requires-Dist: sphinx_copybutton; extra == "dev"
Requires-Dist: pytest; extra == "dev"
Requires-Dist: pytest-timeout; extra == "dev"
Requires-Dist: pylint; extra == "dev"
Requires-Dist: mypy; extra == "dev"
Requires-Dist: responses; extra == "dev"
Provides-Extra: all
Requires-Dist: pyusb; extra == "all"
Requires-Dist: requests; extra == "all"
Requires-Dist: types-requests; extra == "all"
Requires-Dist: pylibftdi; extra == "all"
Requires-Dist: websockets; extra == "all"
Requires-Dist: websockets; extra == "all"
Requires-Dist: opentrons-http-api-client; extra == "all"
Requires-Dist: opentrons-shared-data; extra == "all"
Requires-Dist: flask[async]; extra == "all"
Requires-Dist: hid; extra == "all"
Requires-Dist: sphinx_book_theme; extra == "all"
Requires-Dist: myst_nb; extra == "all"
Requires-Dist: sphinx_copybutton; extra == "all"
Requires-Dist: pytest; extra == "all"
Requires-Dist: pytest-timeout; extra == "all"
Requires-Dist: pylint; extra == "all"
Requires-Dist: mypy; extra == "all"
Requires-Dist: responses; extra == "all"
